odoo/addons/base_phone_popup/README.rst
odoo/addons/base_phone_popup/__init__.py
odoo/addons/base_phone_popup/__manifest__.py
odoo/addons/base_phone_popup/i18n/base_phone_popup.pot
odoo/addons/base_phone_popup/i18n/fr.po
odoo/addons/base_phone_popup/i18n/nl_BE.po
odoo/addons/base_phone_popup/i18n/sl.po
odoo/addons/base_phone_popup/models/__init__.py
odoo/addons/base_phone_popup/models/phone_common.py
odoo/addons/base_phone_popup/models/res_users.py
odoo/addons/base_phone_popup/readme/CONTRIBUTORS.rst
odoo/addons/base_phone_popup/readme/DESCRIPTION.rst
odoo/addons/base_phone_popup/readme/USAGE.rst
odoo/addons/base_phone_popup/static/description/icon.png
odoo/addons/base_phone_popup/static/description/index.html
odoo/addons/base_phone_popup/views/res_users.xml
odoo12_addon_base_phone_popup-12.0.1.0.0.99.dev8.dist-info/METADATA
odoo12_addon_base_phone_popup-12.0.1.0.0.99.dev8.dist-info/WHEEL
odoo12_addon_base_phone_popup-12.0.1.0.0.99.dev8.dist-info/top_level.txt
odoo12_addon_base_phone_popup-12.0.1.0.0.99.dev8.dist-info/RECORD
